pybld/__init__.py
pybld/_bldanaimgc.cpython-311-x86_64-linux-gnu.so
pybld/_pybldc.cpython-311-x86_64-linux-gnu.so
pybld/bldanaimg.py
pybld/bldanaimgc.py
pybld/datafile.py
pybld/grace_np.py
pybld/numpyio.py
pybld/pybldc.py
pybld/qconv.py
PyBLD-4.0.1.dist-info/METADATA
PyBLD-4.0.1.dist-info/WHEEL
PyBLD-4.0.1.dist-info/top_level.txt
PyBLD-4.0.1.dist-info/RECORD
