Metadata-Version: 2.1
Name: PyBLD
Version: 4.0.1
Summary: BLD for Python
Home-page: http://www.rim.cyric.tohoku.ac.jp/pybld/pybld.html
Author: Hiroshi Watabe
Author-email: hwatabe@tohoku.ac.jp
License: GNU Library General Public License (GPL) Version 2
